tobvalid/__init__.py
tobvalid/run.py
tobvalid/local/__init__.py
tobvalid/local/analysis.py
tobvalid/mixture/__init__.py
tobvalid/mixture/_base.py
tobvalid/mixture/gaussian_mixture.py
tobvalid/mixture/invgamma_mixture.py
tobvalid/parsers/__init__.py
tobvalid/parsers/gparser.py
tobvalid/report/__init__.py
tobvalid/report/html_generator.py
tobvalid/report/json_generator.py
tobvalid/report/report.py
tobvalid/stats/__init__.py
tobvalid/stats/outliers.py
tobvalid/stats/pheight.py
tobvalid/stats/silverman.py
tobvalid/templates/albe1.txt
tobvalid/templates/albe2.txt
tobvalid/templates/albe_kde.npy
tobvalid/templates/xx.npy
tobvalid/templates/yy.npy
tobvalid-0.9.7.dist-info/LICENSE
tobvalid-0.9.7.dist-info/METADATA
tobvalid-0.9.7.dist-info/WHEEL
tobvalid-0.9.7.dist-info/entry_points.txt
tobvalid-0.9.7.dist-info/top_level.txt
tobvalid-0.9.7.dist-info/RECORD
