Metadata-Version: 2.1
Name: tobvalid
Version: 0.9.7
Summary: Python library and a program for the statistical analysis and validation of ADPs (Atom Displacement Parameters)
Home-page: https://github.com/ToBvalid/tobvalid
Author: Rafiga Masmaliyeva, Kaveh Babai, Garib N. Murshudov
Author-email: rmasmaliyeva@gmail.com, lekaveh@gmail.com, garib@mrc-lmb.cam.ac.uk
License: MPL-2.0
Platform: UNKNOWN
Requires-Python: >=3
Requires-Dist: pandas
Requires-Dist: matplotlib
Requires-Dist: jsonschema (>=3.2.0)
Requires-Dist: numpy
Requires-Dist: scipy
Requires-Dist: gemmi (>=0.3.8)
Requires-Dist: seaborn
Requires-Dist: statsmodels (>=0.11.1)
Requires-Dist: holoviews (>=1.13.3)
Requires-Dist: panel (>=0.9.5)
